setup.py
Gx/__init__.py
Gx.egg-info/PKG-INFO
Gx.egg-info/SOURCES.txt
Gx.egg-info/dependency_links.txt
Gx.egg-info/top_level.txt
Gx/cv/CreateVideo.py
Gx/cv/Image.py
Gx/cv/__init__.py
Gx/file/__init__.py
Gx/file/get_filename.py
Gx/gxtf/__init__.py
Gx/gxtf/gxtf.py
Gx/np/__init__.py
Gx/time/__init__.py
Gx/time/getTime.py
pyqt/Create_win.py
pyqt/__init__.py